odoo/addons/account_receipt_send/README.rst
odoo/addons/account_receipt_send/__init__.py
odoo/addons/account_receipt_send/__manifest__.py
odoo/addons/account_receipt_send/data/mail_template_data.xml
odoo/addons/account_receipt_send/i18n/account_receipt_send.pot
odoo/addons/account_receipt_send/i18n/es.po
odoo/addons/account_receipt_send/i18n/it.po
odoo/addons/account_receipt_send/models/__init__.py
odoo/addons/account_receipt_send/models/account_move.py
odoo/addons/account_receipt_send/readme/CONFIGURE.rst
odoo/addons/account_receipt_send/readme/CONTRIBUTORS.rst
odoo/addons/account_receipt_send/readme/DESCRIPTION.rst
odoo/addons/account_receipt_send/readme/USAGE.rst
odoo/addons/account_receipt_send/static/description/icon.png
odoo/addons/account_receipt_send/static/description/index.html
odoo/addons/account_receipt_send/tests/__init__.py
odoo/addons/account_receipt_send/tests/test_account_receipt.py
odoo/addons/account_receipt_send/views/account_move_views.xml
odoo_addon_account_receipt_send-16.0.1.0.2.6.dist-info/METADATA
odoo_addon_account_receipt_send-16.0.1.0.2.6.dist-info/WHEEL
odoo_addon_account_receipt_send-16.0.1.0.2.6.dist-info/top_level.txt
odoo_addon_account_receipt_send-16.0.1.0.2.6.dist-info/RECORD
